Workbook

Sheet Overview
A1: NUTRIO FUEL - E2E TEST PLAN
A3: Test Plan Overview
A4: Total Test Cases | B4: =COUNTA('Test Cases'!A:A)-1
A5: Customer Portal Tests | B5: =COUNTIF('Test Cases'!A:A,"*Customer*")
A6: Partner Portal Tests | B6: =COUNTIF('Test Cases'!A:A,"*Partner*")
A7: Admin Portal Tests | B7: =COUNTIF('Test Cases'!A:A,"*Admin*")
A8: Driver Portal Tests | B8: =COUNTIF('Test Cases'!A:A,"*Driver*")
A10: Passed | B10: =COUNTIF('Test Cases'!F:F,"PASS")
A11: Failed | B11: =COUNTIF('Test Cases'!F:F,"FAIL")
A12: Pending | B12: =COUNTIF('Test Cases'!F:F,"PENDING")
A13: Blocked | B13: =COUNTIF('Test Cases'!F:F,"BLOCKED")
A15: Pass Rate | B15: =IF(COUNTA('Test Cases'!F:F)>1,COUNTIF('Test Cases'!F:F,"PASS")/(COUNTA('Test Cases'!F:F)-1),0)
A17: Test Environment Details
A18: Environment | B18: Staging/Production
A19: Test Date
A20: Tester Name
A21: Browser
A22: Device
A23: Notes

Sheet Test Cases
A1: TC ID | B1: Portal | C1: Module | D1: Feature | E1: Test Case | F1: Steps | G1: Expected Result | H1: Status | I1: Actual Result | J1: Notes | K1: Priority | L1: Tester
A2: TC001 | B2: Customer | C2: Auth | D2: Login | E2: Customer Login with Valid Credentials | F2: 1. Navigate to /auth 2. Enter valid email 3. Enter valid password 4. Click Sign In | G2: User logged in and redirected to dashboard | H2: =IF(I2="","",IF(I2=G2,"PASS","FAIL")) | K2: High
A3: TC002 | B3: Customer | C3: Auth | D3: Login | E3: Customer Login with Invalid Password | F3: 1. Navigate to /auth 2. Enter valid email 3. Enter invalid password 4. Click Sign In | G3: Error message: Invalid credentials | H3: =IF(I3="","",IF(I3=G3,"PASS","FAIL")) | K3: High
A4: TC003 | B4: Customer | C4: Auth | D4: Registration | E4: New Customer Registration | F4: 1. Navigate to /auth 2. Click Create Account 3. Fill all required fields 4. Click Sign Up 5. Verify email | G4: Account created successfully, verification email sent | H4: =IF(I4="","",IF(I4=G4,"PASS","FAIL")) | K4: High
A5: TC004 | B5: Customer | C5: Auth | D5: Password Reset | E5: Password Reset Flow | F5: 1. Click Forgot Password 2. Enter email 3. Click Reset 4. Check email 5. Click reset link 6. Enter new password | G5: Password reset successful, can login with new password | H5: =IF(I5="","",IF(I5=G5,"PASS","FAIL")) | K5: Medium
A6: TC005 | B6: Customer | C6: Auth | D6: Logout | E6: Customer Logout | F6: 1. Click user menu 2. Click Logout | G6: User logged out, redirected to login page | H6: =IF(I6="","",IF(I6=G6,"PASS","FAIL")) | K6: High
A7: TC006 | B7: Customer | C7: Dashboard | D7: View | E7: Dashboard Load and Display | F7: 1. Login as customer 2. Navigate to dashboard | G7: Dashboard loads with subscription info, meals remaining, recent orders | H7: =IF(I7="","",IF(I7=G7,"PASS","FAIL")) | K7: High
A8: TC007 | B8: Customer | C8: Dashboard | D8: Navigation | E8: Dashboard Navigation Links | F8: 1. On dashboard 2. Click each navigation link (Meals, Orders, Profile, etc.) | G8: All links navigate to correct pages | H8: =IF(I8="","",IF(I8=G8,"PASS","FAIL")) | K8: High
A9: TC008 | B9: Customer | C9: Dashboard | D9: Quick Actions | E9: Dashboard Quick Action Buttons | F9: 1. On dashboard 2. Click 'Browse Meals' 3. Click 'View Orders' 4. Click 'Refer Friends' | G9: Each button performs correct action | H9: =IF(I9="","",IF(I9=G9,"PASS","FAIL")) | K9: Medium
A10: TC009 | B10: Customer | C10: Subscription | D10: View Plans | E10: View Subscription Plans | F10: 1. Navigate to /subscription 2. View all 4 tiers | G10: All plans displayed with correct pricing and features | H10: =IF(I10="","",IF(I10=G10,"PASS","FAIL")) | K10: High
A11: TC010 | B11: Customer | C11: Subscription | D11: Subscribe Basic | E11: Subscribe to Basic Plan | F11: 1. Click Basic plan 2. Click Subscribe 3. Complete Sadad payment 4. Verify subscription active | G11: Subscription activated, meals allocated | H11: =IF(I11="","",IF(I11=G11,"PASS","FAIL")) | K11: High
A12: TC011 | B12: Customer | C12: Subscription | D12: Subscribe Standard | E12: Subscribe to Standard Plan | F12: 1. Click Standard plan 2. Click Subscribe 3. Complete payment | G12: Subscription activated with 10 meals/week | H12: =IF(I12="","",IF(I12=G12,"PASS","FAIL")) | K12: High
A13: TC012 | B13: Customer | C13: Subscription | D13: Subscribe Premium | E13: Subscribe to Premium Plan | F13: 1. Click Premium plan 2. Complete payment | G13: Subscription activated with 15 meals/week | H13: =IF(I13="","",IF(I13=G13,"PASS","FAIL")) | K13: High
... A163: TC162 | B163: System | C163: Data | D163: Backup | E163: Data Backup Verification | F163: 1. Check backup logs 2. Verify recent backups | G163: Backups running successfully | H163: =IF(I163="","",IF(I163=G163,"PASS","FAIL")) | K163: Medium
A164: TC153 | B164: Partner | C164: Auth | D164: Password Reset | E164: Partner Password Reset Flow | F164: 1. Click Forgot Password on partner login 2. Enter registered email 3. Check email for reset link 4. Click link and set new password 5. Login with new password | G164: Password reset successful, can login with new credentials | K164: High
A165: TC154 | B165: Partner | C165: Onboarding | D165: Wizard Step 1 | E165: Complete Onboarding Step 1 - Basic Info | F165: 1. Start partner registration 2. Fill restaurant name 3. Add description 4. Select cuisine type 5. Add dietary tags | G165: Step 1 saved, can proceed to Step 2 | K165: High
A166: TC155 | B166: Partner | C166: Onboarding | D166: Wizard Step 2 | E166: Complete Onboarding Step 2 - Location | F166: 1. Enter address 2. Pin location on map 3. Add phone number 4. Add email 5. Set operating hours | G166: Step 2 saved, can proceed to Step 3 | K166: High
A167: TC156 | B167: Partner | C167: Onboarding | D167: Wizard Step 3 | E167: Complete Onboarding Step 3 - Media | F167: 1. Upload logo (required) 2. Upload restaurant photos 3. Verify image preview 4. Check file size limits | G167: Images uploaded and preview shown | K167: High
A168: TC157 | B168: Partner | C168: Onboarding | D168: Wizard Step 4 | E168: Complete Onboarding Step 4 - Kitchen Details | F168: 1. Set average prep time 2. Set daily capacity 3. Add bank account info 4. Add bank name and IBAN | G168: Kitchen details saved, can proceed to Step 5 | K168: Critical
A169: TC158 | B169: Partner | C169: Onboarding | D169: Wizard Step 5 | E169: Complete Onboarding Step 5 - Review & Submit | F169: 1. Review all entered information 2. Check accuracy of details 3. Accept terms and conditions 4. Click Submit | G169: Application submitted, status shows 'pending_approval' | K169: Critical
A170: TC159 | B170: Partner | C170: Onboarding | D170: Save Progress | E170: Save Onboarding Progress | F170: 1. Fill partial information 2. Click Save Progress 3. Logout 4. Login again 5. Continue from where left off | G170: Progress saved, can resume onboarding | K170: Medium
A171: TC160 | B171: Partner | C171: Dashboard | D171: Real-time Updates | E171: Dashboard Real-time Order Updates | F171: 1. Keep dashboard open 2. Have customer place order 3. Verify order appears without refresh 4. Check notification received | G171: New order appears automatically on dashboard | K171: High
A172: TC161 | B172: Partner | C172: Dashboard | D172: Performance Chart | E172: View Performance Charts | F172: 1. On dashboard, scroll to charts 2. View orders chart 3. View earnings chart 4. Hover for detailed values | G172: Charts display correctly with accurate data | K172: Low
A173: TC162 | B173: Partner | C173: Dashboard | D173: Recent Orders | E173: View Recent Orders on Dashboard | F173: 1. Look at Recent Orders section 2. Click View All 3. Verify navigation to Orders page | G173: Recent orders displayed, click navigates to full orders page | K173: Medium
A174: TC163 | B174: Partner | C174: Dashboard | D174: Quick Stats | E174: Dashboard Quick Stats Cards | F174: 1. Verify Today's Orders card 2. Verify Today's Earnings card 3. Verify Weekly Total card 4. Verify Rating card 5. Check all values are accurate | G174: All stat cards show correct information | K174: High
A175: TC164 | B175: Partner | C175: Orders | D175: Bulk Actions | E175: Bulk Order Actions | F175: 1. Select multiple orders 2. Click bulk action 3. Mark all as preparing 4. Verify all updated | G175: All selected orders updated to new status | K175: Low
... A257: TC199 | B257: Partner | C257: Support | D257: Live Chat | E257: Start Live Chat | F257: 1. Click Chat icon 2. Start conversation 3. Send message 4. Receive response | G257: Chat connected, messages exchanged | K257: Medium

Sheet Summary by Portal
A1: Portal | B1: Total Tests | C1: Passed | D1: Failed | E1: Pending | F1: Pass Rate | G1: Critical | H1: High | I1: Medium | J1: Low
A2: Customer | B2: =COUNTIF('Test Cases'!B:B,A2) | C2: =COUNTIFS('Test Cases'!B:B,A2,'Test Cases'!H:H,"PASS") | D2: =COUNTIFS('Test Cases'!B:B,A2,'Test Cases'!H:H,"FAIL") | E2: =COUNTIFS('Test Cases'!B:B,A2,'Test Cases'!H:H,"") | F2: =IF(B2>0,C2/B2,0) | G2: =COUNTIFS('Test Cases'!B:B,A2,'Test Cases'!K:K,"Critical") | H2: =COUNTIFS('Test Cases'!B:B,A2,'Test Cases'!K:K,"High") | I2: =COUNTIFS('Test Cases'!B:B,A2,'Test Cases'!K:K,"Medium") | J2: =COUNTIFS('Test Cases'!B:B,A2,'Test Cases'!K:K,"Low")
A3: Partner | B3: =COUNTIF('Test Cases'!B:B,A3) | C3: =COUNTIFS('Test Cases'!B:B,A3,'Test Cases'!H:H,"PASS") | D3: =COUNTIFS('Test Cases'!B:B,A3,'Test Cases'!H:H,"FAIL") | E3: =COUNTIFS('Test Cases'!B:B,A3,'Test Cases'!H:H,"") | F3: =IF(B3>0,C3/B3,0) | G3: =COUNTIFS('Test Cases'!B:B,A3,'Test Cases'!K:K,"Critical") | H3: =COUNTIFS('Test Cases'!B:B,A3,'Test Cases'!K:K,"High") | I3: =COUNTIFS('Test Cases'!B:B,A3,'Test Cases'!K:K,"Medium") | J3: =COUNTIFS('Test Cases'!B:B,A3,'Test Cases'!K:K,"Low")
A4: Admin | B4: =COUNTIF('Test Cases'!B:B,A4) | C4: =COUNTIFS('Test Cases'!B:B,A4,'Test Cases'!H:H,"PASS") | D4: =COUNTIFS('Test Cases'!B:B,A4,'Test Cases'!H:H,"FAIL") | E4: =COUNTIFS('Test Cases'!B:B,A4,'Test Cases'!H:H,"") | F4: =IF(B4>0,C4/B4,0) | G4: =COUNTIFS('Test Cases'!B:B,A4,'Test Cases'!K:K,"Critical") | H4: =COUNTIFS('Test Cases'!B:B,A4,'Test Cases'!K:K,"High") | I4: =COUNTIFS('Test Cases'!B:B,A4,'Test Cases'!K:K,"Medium") | J4: =COUNTIFS('Test Cases'!B:B,A4,'Test Cases'!K:K,"Low")
A5: Driver | B5: =COUNTIF('Test Cases'!B:B,A5) | C5: =COUNTIFS('Test Cases'!B:B,A5,'Test Cases'!H:H,"PASS") | D5: =COUNTIFS('Test Cases'!B:B,A5,'Test Cases'!H:H,"FAIL") | E5: =COUNTIFS('Test Cases'!B:B,A5,'Test Cases'!H:H,"") | F5: =IF(B5>0,C5/B5,0) | G5: =COUNTIFS('Test Cases'!B:B,A5,'Test Cases'!K:K,"Critical") | H5: =COUNTIFS('Test Cases'!B:B,A5,'Test Cases'!K:K,"High") | I5: =COUNTIFS('Test Cases'!B:B,A5,'Test Cases'!K:K,"Medium") | J5: =COUNTIFS('Test Cases'!B:B,A5,'Test Cases'!K:K,"Low")
A6: System | B6: =COUNTIF('Test Cases'!B:B,A6) | C6: =COUNTIFS('Test Cases'!B:B,A6,'Test Cases'!H:H,"PASS") | D6: =COUNTIFS('Test Cases'!B:B,A6,'Test Cases'!H:H,"FAIL") | E6: =COUNTIFS('Test Cases'!B:B,A6,'Test Cases'!H:H,"") | F6: =IF(B6>0,C6/B6,0) | G6: =COUNTIFS('Test Cases'!B:B,A6,'Test Cases'!K:K,"Critical") | H6: =COUNTIFS('Test Cases'!B:B,A6,'Test Cases'!K:K,"High") | I6: =COUNTIFS('Test Cases'!B:B,A6,'Test Cases'!K:K,"Medium") | J6: =COUNTIFS('Test Cases'!B:B,A6,'Test Cases'!K:K,"Low")
